py_librescore/__init__.py
py_librescore/__main__.py
py_librescore/api.py
py_librescore/auth.py
py_librescore/core.py
py_librescore/downloader.py
py_librescore/exceptions.py
py_librescore/file.py
py_librescore/parser.py
py_librescore/pdf.py
py_librescore/types.py
py_librescore/utils.py
py_librescore-1.0.1.dist-info/licenses/LICENSE
py_librescore-1.0.1.dist-info/METADATA
py_librescore-1.0.1.dist-info/WHEEL
py_librescore-1.0.1.dist-info/entry_points.txt
py_librescore-1.0.1.dist-info/top_level.txt
py_librescore-1.0.1.dist-info/RECORD
