Metadata-Version: 2.4
Name: py-librescore
Version: 1.0.1
Summary: Download sheet music from MuseScore
Author: kikkopy
License: MIT
Project-URL: Homepage, https://github.com/kikkopy/py-librescore
Project-URL: Repository, https://github.com/kikkopy/py-librescore
Project-URL: Bug Reports, https://github.com/kikkopy/py-librescore/issues
Keywords: musescore,music,sheet-music,download,pdf,midi,mp3
Classifier: Development Status :: 4 - Beta
Classifier: Intended Audience :: End Users/Desktop
Classifier: License :: OSI Approved :: MIT License
Classifier: Operating System :: OS Independent
Classifier: Programming Language :: Python :: 3
Classifier: Programming Language :: Python :: 3.7
Classifier: Programming Language :: Python :: 3.8
Classifier: Programming Language :: Python :: 3.9
Classifier: Programming Language :: Python :: 3.10
Classifier: Programming Language :: Python :: 3.11
Classifier: Topic :: Multimedia :: Sound/Audio
Classifier: Topic :: Utilities
Requires-Python: >=3.7
License-File: LICENSE
Requires-Dist: requests>=2.31.0
Requires-Dist: reportlab>=4.0.0
Requires-Dist: Pillow>=10.0.0
Dynamic: license-file
